yt_fzf.py
yt_fzf-0.1.6.dist-info/METADATA
yt_fzf-0.1.6.dist-info/WHEEL
yt_fzf-0.1.6.dist-info/entry_points.txt
yt_fzf-0.1.6.dist-info/licenses/LICENSE
yt_fzf-0.1.6.dist-info/RECORD
