Metadata-Version: 2.4
Name: yt-fzf
Version: 0.1.6
Summary: Search and download music from YouTube using fzf and yt-dlp.
License: BSD
License-File: LICENSE
Author: Simone Gentili
Author-email: gensimone.git@gmail.com
Requires-Python: >=3.8,<4.0
Classifier: License :: Other/Proprietary License
Classifier: Programming Language :: Python :: 3
Classifier: Programming Language :: Python :: 3.8
Classifier: Programming Language :: Python :: 3.9
Classifier: Programming Language :: Python :: 3.10
Classifier: Programming Language :: Python :: 3.11
Classifier: Programming Language :: Python :: 3.12
Classifier: Programming Language :: Python :: 3.13
Classifier: Programming Language :: Python :: 3.14
Requires-Dist: innertube
